histogis/__init__.py
histogis/histogis.py
acdh_histogis-0.0.5.dist-info/LICENSE.txt
acdh_histogis-0.0.5.dist-info/METADATA
acdh_histogis-0.0.5.dist-info/WHEEL
acdh_histogis-0.0.5.dist-info/top_level.txt
acdh_histogis-0.0.5.dist-info/RECORD
